LICENSE
MANIFEST.in
README.md
setup.py
GitLabRC.egg-info/PKG-INFO
GitLabRC.egg-info/SOURCES.txt
GitLabRC.egg-info/dependency_links.txt
GitLabRC.egg-info/entry_points.txt
GitLabRC.egg-info/not-zip-safe
GitLabRC.egg-info/requires.txt
GitLabRC.egg-info/top_level.txt
gitlabrc/__init__.py
gitlabrc/__main__.py
gitlabrc/arguments.py
gitlabrc/base.py
gitlabrc/cli.py
gitlabrc/constants.py
gitlabrc/log.py
gitlabrc/process.py
gitlabrc/progress.py
gitlabrc/settings.py
gitlabrc/tree.py