Metadata-Version: 2.1
Name: GitLabRC
Version: 1.1.0
Summary: GitlabRC is a python CLI that help you to clone projects inside namespace (groups) in Gitlab
Home-page: https://github.com/lpmatos/gitlabrc
Author: Lucca Pessoa da Silva Matos
Author-email: luccapsm@gmail.com
License: MIT license
Keywords: git,cli,python,gitlab,gitlab-cli
Platform: UNKNOWN
Requires-Python: >=3.6.0
